{
    "metadata": {
        "app_name": "OMEGA PRO AI",
        "version": "v12.0",
        "export_date": "2025-08-01T18:53:15.579053",
        "parameters": {
            "data_path": "data/historial_kabala_github.csv",
            "svi_profile": "default",
            "top_n": 30,
            "enable_models": [
                "consensus",
                "ghost_rng",
                "inverse_mining",
                "lstm_v2",
                "montecarlo",
                "apriori",
                "transformer_deep",
                "clustering",
                "genetico"
            ]
        }
    },
    "combinations": [
        {
            "rank": 1,
            "source": "apriori",
            "combination": [
                9,
                16,
                24,
                27,
                31,
                37
            ],
            "score": 1.01348472,
            "svi_score": 0.5,
            "original_score": 1.2335496
        },
        {
            "rank": 2,
            "source": "transformer_deep",
            "combination": [
                4,
                11,
                14,
                25,
                26,
                31
            ],
            "score": 0.9545015999999998,
            "svi_score": 0.5,
            "original_score": 1.1492879999999999
        },
        {
            "rank": 3,
            "source": "apriori",
            "combination": [
                5,
                11,
                24,
                28,
                35,
                39
            ],
            "score": 0.7256419199999999,
            "svi_score": 0.5,
            "original_score": 0.8223456
        },
        {
            "rank": 4,
            "source": "apriori",
            "combination": [
                1,
                11,
                14,
                23,
                24,
                25
            ],
            "score": 0.7232238400000001,
            "svi_score": 0.5,
            "original_score": 0.8188912
        },
        {
            "rank": 5,
            "source": "montecarlo",
            "combination": [
                10,
                11,
                20,
                25,
                37,
                38
            ],
            "score": 0.6875350400000001,
            "svi_score": 0.5,
            "original_score": 0.7679072000000001
        },
        {
            "rank": 6,
            "source": "lstm_v2",
            "combination": [
                6,
                12,
                18,
                24,
                29,
                35
            ],
            "score": 0.6864206399999999,
            "svi_score": 0.5,
            "original_score": 0.7663152
        },
        {
            "rank": 7,
            "source": "transformer_deep",
            "combination": [
                1,
                6,
                11,
                16,
                27,
                32
            ],
            "score": 0.68489744,
            "svi_score": 0.5,
            "original_score": 0.7641391999999999
        },
        {
            "rank": 8,
            "source": "apriori",
            "combination": [
                5,
                9,
                15,
                24,
                26,
                31
            ],
            "score": 0.43781928000000003,
            "svi_score": 0.5,
            "original_score": 0.41117040000000005
        },
        {
            "rank": 9,
            "source": "apriori",
            "combination": [
                5,
                10,
                14,
                21,
                26,
                32
            ],
            "score": 0.43771119999999997,
            "svi_score": 0.5,
            "original_score": 0.411016
        },
        {
            "rank": 10,
            "source": "genetico",
            "combination": [
                3,
                10,
                19,
                21,
                24,
                34
            ],
            "score": 0.4376602399999999,
            "svi_score": 0.5,
            "original_score": 0.41094319999999995
        },
        {
            "rank": 11,
            "source": "genetico",
            "combination": [
                9,
                18,
                19,
                20,
                27,
                35
            ],
            "score": 0.43755272,
            "svi_score": 0.5,
            "original_score": 0.41078960000000003
        },
        {
            "rank": 12,
            "source": "genetico",
            "combination": [
                3,
                5,
                15,
                16,
                20,
                37
            ],
            "score": 0.43732647999999996,
            "svi_score": 0.5,
            "original_score": 0.41046639999999995
        },
        {
            "rank": 13,
            "source": "genetico",
            "combination": [
                3,
                7,
                8,
                13,
                20,
                33
            ],
            "score": 0.43718703999999997,
            "svi_score": 0.5,
            "original_score": 0.4102672
        },
        {
            "rank": 14,
            "source": "apriori",
            "combination": [
                1,
                6,
                11,
                15,
                22,
                28
            ],
            "score": 0.43653856,
            "svi_score": 0.5,
            "original_score": 0.4093408
        },
        {
            "rank": 15,
            "source": "apriori",
            "combination": [
                2,
                8,
                24,
                32,
                34,
                40
            ],
            "score": 0.43254631999999993,
            "svi_score": 0.5,
            "original_score": 0.4036376
        },
        {
            "rank": 16,
            "source": "clustering",
            "combination": [
                8,
                11,
                18,
                24,
                29,
                32
            ],
            "score": 0.43028616,
            "svi_score": 0.5,
            "original_score": 0.4004088
        },
        {
            "rank": 17,
            "source": "clustering",
            "combination": [
                5,
                7,
                17,
                20,
                26,
                31
            ],
            "score": 0.42981800000000003,
            "svi_score": 0.5,
            "original_score": 0.39974000000000004
        },
        {
            "rank": 18,
            "source": "clustering",
            "combination": [
                5,
                14,
                19,
                23,
                24,
                32
            ],
            "score": 0.42686848,
            "svi_score": 0.5,
            "original_score": 0.3955264
        },
        {
            "rank": 19,
            "source": "ghost_rng",
            "combination": [
                1,
                2,
                7,
                16,
                18,
                28
            ],
            "score": 0.42606992,
            "svi_score": 0.5,
            "original_score": 0.39438559999999995
        },
        {
            "rank": 20,
            "source": "montecarlo",
            "combination": [
                11,
                15,
                20,
                25,
                35,
                40
            ],
            "score": 0.41922335999999993,
            "svi_score": 0.5,
            "original_score": 0.38460479999999997
        },
        {
            "rank": 21,
            "source": "montecarlo",
            "combination": [
                12,
                13,
                19,
                24,
                25,
                36
            ],
            "score": 0.4186291999999999,
            "svi_score": 0.5,
            "original_score": 0.383756
        },
        {
            "rank": 22,
            "source": "montecarlo",
            "combination": [
                3,
                11,
                21,
                22,
                27,
                34
            ],
            "score": 0.41862807999999996,
            "svi_score": 0.5,
            "original_score": 0.3837544
        },
        {
            "rank": 23,
            "source": "montecarlo",
            "combination": [
                6,
                9,
                11,
                24,
                27,
                32
            ],
            "score": 0.41852504,
            "svi_score": 0.5,
            "original_score": 0.38360720000000004
        },
        {
            "rank": 24,
            "source": "transformer_deep",
            "combination": [
                4,
                5,
                7,
                29,
                35,
                36
            ],
            "score": 0.41841527999999995,
            "svi_score": 0.5,
            "original_score": 0.38345039999999997
        },
        {
            "rank": 25,
            "source": "transformer_deep",
            "combination": [
                1,
                11,
                28,
                29,
                36,
                38
            ],
            "score": 0.41830384,
            "svi_score": 0.5,
            "original_score": 0.38329119999999994
        },
        {
            "rank": 26,
            "source": "clustering",
            "combination": [
                13,
                14,
                17,
                27,
                35,
                36
            ],
            "score": 0.41805687999999996,
            "svi_score": 0.5,
            "original_score": 0.38293839999999996
        },
        {
            "rank": 27,
            "source": "transformer_deep",
            "combination": [
                4,
                6,
                17,
                28,
                32,
                33
            ],
            "score": 0.41805408,
            "svi_score": 0.5,
            "original_score": 0.38293439999999995
        },
        {
            "rank": 28,
            "source": "clustering",
            "combination": [
                4,
                7,
                11,
                22,
                28,
                39
            ],
            "score": 0.41804904,
            "svi_score": 0.5,
            "original_score": 0.38292719999999997
        },
        {
            "rank": 29,
            "source": "montecarlo",
            "combination": [
                6,
                10,
                16,
                20,
                24,
                40
            ],
            "score": 0.41798576,
            "svi_score": 0.5,
            "original_score": 0.38283680000000003
        },
        {
            "rank": 30,
            "source": "montecarlo",
            "combination": [
                2,
                4,
                9,
                13,
                21,
                40
            ],
            "score": 0.41759767999999997,
            "svi_score": 0.5,
            "original_score": 0.3822824
        }
    ]
}