{
  "metadata": {
    "system": "OMEGA PRO AI - Meta-Learning",
    "timestamp": "20250808_171306",
    "total_predictions": 8,
    "components_used": 4,
    "data_size": 3646
  },
  "predictions": [
    {
      "combination": [
        "14",
        "16",
        "21",
        "29",
        "30",
        "32"
      ],
      "confidence": 0.6,
      "source": "meta_learning_hybrid",
      "components_used": [
        "meta_controller"
      ],
      "meta_weights": {
        "lstm_v2": 1.0514866980142832,
        "transformer": 1.0514866980142832,
        "clustering": 1.0514866980142832,
        "montecarlo": 1.0514866980142832,
        "genetic": 1.0514866980142832,
        "gboost": 1.0514866980142832,
        "ensemble_ai": 1.5772300470214247
      },
      "timestamp": "2025-08-08T17:13:06.943094"
    },
    {
      "combination": [
        "3",
        "10",
        "11",
        "27",
        "30",
        "40"
      ],
      "confidence": 0.6,
      "source": "meta_learning_hybrid",
      "components_used": [
        "meta_controller"
      ],
      "meta_weights": {
        "lstm_v2": 1.0514866980142832,
        "transformer": 1.0514866980142832,
        "clustering": 1.0514866980142832,
        "montecarlo": 1.0514866980142832,
        "genetic": 1.0514866980142832,
        "gboost": 1.0514866980142832,
        "ensemble_ai": 1.5772300470214247
      },
      "timestamp": "2025-08-08T17:13:06.943283"
    },
    {
      "combination": [
        "1",
        "9",
        "11",
        "18",
        "20",
        "38"
      ],
      "confidence": 0.6,
      "source": "meta_learning_hybrid",
      "components_used": [
        "meta_controller"
      ],
      "meta_weights": {
        "lstm_v2": 1.0514866980142832,
        "transformer": 1.0514866980142832,
        "clustering": 1.0514866980142832,
        "montecarlo": 1.0514866980142832,
        "genetic": 1.0514866980142832,
        "gboost": 1.0514866980142832,
        "ensemble_ai": 1.5772300470214247
      },
      "timestamp": "2025-08-08T17:13:06.943546"
    },
    {
      "combination": [
        "12",
        "21",
        "23",
        "27",
        "28",
        "30"
      ],
      "confidence": 0.6,
      "source": "meta_learning_hybrid",
      "components_used": [
        "meta_controller"
      ],
      "meta_weights": {
        "lstm_v2": 1.0514866980142832,
        "transformer": 1.0514866980142832,
        "clustering": 1.0514866980142832,
        "montecarlo": 1.0514866980142832,
        "genetic": 1.0514866980142832,
        "gboost": 1.0514866980142832,
        "ensemble_ai": 1.5772300470214247
      },
      "timestamp": "2025-08-08T17:13:06.943725"
    },
    {
      "combination": [
        "1",
        "2",
        "10",
        "13",
        "14",
        "35"
      ],
      "confidence": 0.6,
      "source": "meta_learning_hybrid",
      "components_used": [
        "meta_controller"
      ],
      "meta_weights": {
        "lstm_v2": 1.0514866980142832,
        "transformer": 1.0514866980142832,
        "clustering": 1.0514866980142832,
        "montecarlo": 1.0514866980142832,
        "genetic": 1.0514866980142832,
        "gboost": 1.0514866980142832,
        "ensemble_ai": 1.5772300470214247
      },
      "timestamp": "2025-08-08T17:13:06.943918"
    },
    {
      "combination": [
        "1",
        "9",
        "11",
        "15",
        "17",
        "23"
      ],
      "confidence": 0.6,
      "source": "meta_learning_hybrid",
      "components_used": [
        "meta_controller"
      ],
      "meta_weights": {
        "lstm_v2": 1.0514866980142832,
        "transformer": 1.0514866980142832,
        "clustering": 1.0514866980142832,
        "montecarlo": 1.0514866980142832,
        "genetic": 1.0514866980142832,
        "gboost": 1.0514866980142832,
        "ensemble_ai": 1.5772300470214247
      },
      "timestamp": "2025-08-08T17:13:06.944092"
    },
    {
      "combination": [
        "1",
        "2",
        "16",
        "17",
        "33",
        "38"
      ],
      "confidence": 0.6,
      "source": "meta_learning_hybrid",
      "components_used": [
        "meta_controller"
      ],
      "meta_weights": {
        "lstm_v2": 1.0514866980142832,
        "transformer": 1.0514866980142832,
        "clustering": 1.0514866980142832,
        "montecarlo": 1.0514866980142832,
        "genetic": 1.0514866980142832,
        "gboost": 1.0514866980142832,
        "ensemble_ai": 1.5772300470214247
      },
      "timestamp": "2025-08-08T17:13:06.944268"
    },
    {
      "combination": [
        "7",
        "13",
        "17",
        "21",
        "23",
        "38"
      ],
      "confidence": 0.6,
      "source": "meta_learning_hybrid",
      "components_used": [
        "meta_controller"
      ],
      "meta_weights": {
        "lstm_v2": 1.0514866980142832,
        "transformer": 1.0514866980142832,
        "clustering": 1.0514866980142832,
        "montecarlo": 1.0514866980142832,
        "genetic": 1.0514866980142832,
        "gboost": 1.0514866980142832,
        "ensemble_ai": 1.5772300470214247
      },
      "timestamp": "2025-08-08T17:13:06.944462"
    }
  ],
  "meta_analysis": {
    "regime": "moderate_balanced",
    "entropy": 0.9998040585479516,
    "variance": 5.631515098554868,
    "trend_strength": 9.176684498200751e-07,
    "optimal_weights": {
      "lstm_v2": 1.0,
      "transformer": 1.0,
      "clustering": 1.0,
      "montecarlo": 1.0,
      "genetic": 1.0,
      "gboost": 1.0,
      "ensemble_ai": 1.5
    }
  },
  "component_results": {
    "profiler": {
      "profile": "moderate_mixed",
      "confidence": 0.5,
      "probability_distribution": {
        "moderate_mixed": 0.5
      }
    },
    "reinforcement": {
      "action_type": "ADJUST_THRESHOLD",
      "model_adjusted": "montecarlo",
      "adjustment_value": 0.05148669801428314,
      "epsilon": 1.0
    }
  },
  "integration_metrics": {
    "processing_time": 0.069092,
    "components_used": 4,
    "predictions_generated": 8,
    "weights_optimized": 7,
    "confidence_avg": 0.6
  }
}