{
  "metadata": {
    "system": "OMEGA PRO AI - Meta-Learning",
    "timestamp": "20250819_165034",
    "total_predictions": 8,
    "components_used": 4,
    "data_size": 1000
  },
  "predictions": [
    {
      "combination": [
        1,
        2,
        5,
        32,
        39,
        40
      ],
      "confidence": 0.3988253355026245,
      "source": "meta_learning_integrated",
      "components_used": [
        "lstm_v2",
        "meta_controller",
        "reinforcement_learning",
        "dynamic_profiler"
      ],
      "meta_weights": {
        "lstm_v2": 1.2,
        "transformer": 1.1,
        "clustering": 1.0,
        "montecarlo": 1.0,
        "genetic": 1.0,
        "gboost": 1.0,
        "ensemble_ai": 1.5
      },
      "timestamp": "2025-08-19T16:50:34.340326"
    },
    {
      "combination": [
        1,
        2,
        5,
        12,
        28,
        40
      ],
      "confidence": 0.39864764213562015,
      "source": "meta_learning_integrated",
      "components_used": [
        "lstm_v2",
        "meta_controller",
        "reinforcement_learning",
        "dynamic_profiler"
      ],
      "meta_weights": {
        "lstm_v2": 1.2,
        "transformer": 1.1,
        "clustering": 1.0,
        "montecarlo": 1.0,
        "genetic": 1.0,
        "gboost": 1.0,
        "ensemble_ai": 1.5
      },
      "timestamp": "2025-08-19T16:50:34.340330"
    },
    {
      "combination": [
        9,
        10,
        16,
        32,
        33,
        34
      ],
      "confidence": 0.39864764213562015,
      "source": "meta_learning_integrated",
      "components_used": [
        "lstm_v2",
        "meta_controller",
        "reinforcement_learning",
        "dynamic_profiler"
      ],
      "meta_weights": {
        "lstm_v2": 1.2,
        "transformer": 1.1,
        "clustering": 1.0,
        "montecarlo": 1.0,
        "genetic": 1.0,
        "gboost": 1.0,
        "ensemble_ai": 1.5
      },
      "timestamp": "2025-08-19T16:50:34.340332"
    },
    {
      "combination": [
        1,
        11,
        14,
        27,
        34,
        36
      ],
      "confidence": 0.3986719608306885,
      "source": "meta_learning_integrated",
      "components_used": [
        "lstm_v2",
        "meta_controller",
        "reinforcement_learning",
        "dynamic_profiler"
      ],
      "meta_weights": {
        "lstm_v2": 1.2,
        "transformer": 1.1,
        "clustering": 1.0,
        "montecarlo": 1.0,
        "genetic": 1.0,
        "gboost": 1.0,
        "ensemble_ai": 1.5
      },
      "timestamp": "2025-08-19T16:50:34.340334"
    },
    {
      "combination": [
        1,
        11,
        12,
        16,
        26,
        34
      ],
      "confidence": 0.39864764213562015,
      "source": "meta_learning_integrated",
      "components_used": [
        "lstm_v2",
        "meta_controller",
        "reinforcement_learning",
        "dynamic_profiler"
      ],
      "meta_weights": {
        "lstm_v2": 1.2,
        "transformer": 1.1,
        "clustering": 1.0,
        "montecarlo": 1.0,
        "genetic": 1.0,
        "gboost": 1.0,
        "ensemble_ai": 1.5
      },
      "timestamp": "2025-08-19T16:50:34.340336"
    },
    {
      "combination": [
        1,
        7,
        15,
        16,
        22,
        24
      ],
      "confidence": 0.39864764213562015,
      "source": "meta_learning_integrated",
      "components_used": [
        "lstm_v2",
        "meta_controller",
        "reinforcement_learning",
        "dynamic_profiler"
      ],
      "meta_weights": {
        "lstm_v2": 1.2,
        "transformer": 1.1,
        "clustering": 1.0,
        "montecarlo": 1.0,
        "genetic": 1.0,
        "gboost": 1.0,
        "ensemble_ai": 1.5
      },
      "timestamp": "2025-08-19T16:50:34.340338"
    },
    {
      "combination": [
        1,
        2,
        21,
        27,
        33,
        39
      ],
      "confidence": 0.39864764213562015,
      "source": "meta_learning_integrated",
      "components_used": [
        "lstm_v2",
        "meta_controller",
        "reinforcement_learning",
        "dynamic_profiler"
      ],
      "meta_weights": {
        "lstm_v2": 1.2,
        "transformer": 1.1,
        "clustering": 1.0,
        "montecarlo": 1.0,
        "genetic": 1.0,
        "gboost": 1.0,
        "ensemble_ai": 1.5
      },
      "timestamp": "2025-08-19T16:50:34.340339"
    },
    {
      "combination": [
        7,
        14,
        16,
        29,
        30,
        32
      ],
      "confidence": 0.39864764213562015,
      "source": "meta_learning_integrated",
      "components_used": [
        "lstm_v2",
        "meta_controller",
        "reinforcement_learning",
        "dynamic_profiler"
      ],
      "meta_weights": {
        "lstm_v2": 1.2,
        "transformer": 1.1,
        "clustering": 1.0,
        "montecarlo": 1.0,
        "genetic": 1.0,
        "gboost": 1.0,
        "ensemble_ai": 1.5
      },
      "timestamp": "2025-08-19T16:50:34.340341"
    }
  ],
  "meta_analysis": {
    "regime": "balanced",
    "entropy": 5.317712404543903,
    "variance": 133.55011641666667,
    "trend_strength": 0.7333333333333333,
    "optimal_weights": {
      "lstm_v2": 1.2,
      "transformer": 1.1,
      "clustering": 1.0,
      "montecarlo": 1.0,
      "genetic": 1.0,
      "gboost": 1.0,
      "ensemble_ai": 1.5
    },
    "context_optimization": {
      "high_entropy_mode": "True",
      "no_trend_mode": false,
      "uncertainty_level": "very_high"
    }
  },
  "component_results": {
    "profiler": {
      "profile": "high_frequency_stable",
      "confidence": 0.5297911167702142,
      "original_confidence": 0.6020353599661524,
      "probability_distribution": {
        "high_frequency_stable": 0.6020353599661524,
        "low_frequency_chaotic": 0.09409480551310272,
        "moderate_mixed": 0.30386983452074484
      },
      "confidence_enhancement": -0.07224424319593825
    },
    "lstm_v2": {
      "predictions_count": 8,
      "avg_confidence": 0.498341117054224,
      "is_trained": true,
      "training_attempted": false
    },
    "reinforcement": {
      "action_type": "COMBINE_MODELS",
      "model_adjusted": "montecarlo",
      "adjustment_value": -0.02278043362296427,
      "epsilon": 1.0
    }
  },
  "integration_metrics": {
    "processing_time": 36.597671,
    "components_used": 4,
    "predictions_generated": 8,
    "weights_optimized": 7,
    "confidence_avg": 0.3986728936433792
  }
}